vidtoolz_add_sound/__init__.py
vidtoolz_add_sound/add_sound.py
vidtoolz_add_sound-0.0.1.dist-info/LICENSE
vidtoolz_add_sound-0.0.1.dist-info/METADATA
vidtoolz_add_sound-0.0.1.dist-info/WHEEL
vidtoolz_add_sound-0.0.1.dist-info/entry_points.txt
vidtoolz_add_sound-0.0.1.dist-info/top_level.txt
vidtoolz_add_sound-0.0.1.dist-info/RECORD
