Metadata-Version: 2.2
Name: vidtoolz-add-sound
Version: 0.0.1
Summary: Add sound to a video
Author: Sukhbinder Singh
License: Apache-2.0
Project-URL: Homepage, https://github.com/sukhbinder/vidtoolz-add-sound
Project-URL: Changelog, https://github.com/sukhbinder/vidtoolz-add-sound/releases
Project-URL: Issues, https://github.com/sukhbinder/vidtoolz-add-sound/issues
Project-URL: CI, https://github.com/sukhbinder/vidtoolz-add-sound/actions
Classifier: License :: OSI Approved :: Apache Software License
License-File: LICENSE
Requires-Dist: vidtoolz
Provides-Extra: test
Requires-Dist: pytest; extra == "test"
